spider_core/__init__.py
spider_core/config.py
spider_core/http_spider.py
spider_core/main.py
spider_core/serverapi.py
spider_core/utils.py
spider_core/temp/.gitignore
spider_core/temp/main.py.temp
spider_core/temp/http_scrapy_temp/scrapy.cfg.temp
spider_core/temp/http_scrapy_temp/project/__init__.py
spider_core/temp/http_scrapy_temp/project/items.py.temp
spider_core/temp/http_scrapy_temp/project/middlewares.py.temp
spider_core/temp/http_scrapy_temp/project/pipelines.py.temp
spider_core/temp/http_scrapy_temp/project/settings.py.temp
spider_core/temp/http_scrapy_temp/project/spiders/__init__.py
spider_core/temp/http_scrapy_temp/project/spiders/spider.py.temp
spider_core_sdk-1.4.9.dist-info/METADATA
spider_core_sdk-1.4.9.dist-info/WHEEL
spider_core_sdk-1.4.9.dist-info/entry_points.txt
spider_core_sdk-1.4.9.dist-info/top_level.txt
spider_core_sdk-1.4.9.dist-info/RECORD
