Metadata-Version: 2.1
Name: spider-core-sdk
Version: 1.4.9
Summary: UNKNOWN
Home-page: UNKNOWN
Author: wog
License: UNKNOWN
Platform: UNKNOWN
Classifier: Development Status :: 5 - Production/Stable
Classifier: Intended Audience :: Developers
Classifier: License :: OSI Approved :: Apache Software License
Classifier: Programming Language :: Python
Classifier: Programming Language :: Python :: 3.7
Classifier: Programming Language :: Python :: 3.8
Classifier: Programming Language :: Python :: 3.9
Classifier: Programming Language :: Python :: Implementation :: CPython
Requires-Python: >=3.7
Requires-Dist: likeshell (>=1.1.5)
Requires-Dist: jinja2
Requires-Dist: requests
Requires-Dist: termcolor
